{
  "id": "47645af7-fa4a-473b-8943-bc147c201cd4",
  "prevId": "679834a4-319a-4615-b88e-8eee4e81d08b",
  "version": "7",
  "dialect": "postgresql",
  "tables": {
    "public.bookslist": {
      "name": "bookslist",
      "schema": "",
      "columns": {
        "id": {
          "name": "id",
          "type": "serial",
          "primaryKey": false,
          "notNull": true
        },
        "email": {
          "name": "email",
          "type": "varchar(255)",
          "primaryKey": false,
          "notNull": false
        },
        "title": {
          "name": "title",
          "type": "varchar(30)",
          "primaryKey": false,
          "notNull": true
        },
        "author": {
          "name": "author",
          "type": "varchar(30)",
          "primaryKey": false,
          "notNull": true
        },
        "genre": {
          "name": "genre",
          "type": "text[]",
          "primaryKey": false,
          "notNull": false
        }
      },
      "indexes": {},
      "foreignKeys": {
        "bookslist_email_users_email_fk": {
          "name": "bookslist_email_users_email_fk",
          "tableFrom": "bookslist",
          "tableTo": "users",
          "columnsFrom": [
            "email"
          ],
          "columnsTo": [
            "email"
          ],
          "onDelete": "cascade",
          "onUpdate": "cascade"
        }
      },
      "compositePrimaryKeys": {},
      "uniqueConstraints": {}
    },
    "public.users": {
      "name": "users",
      "schema": "",
      "columns": {
        "id": {
          "name": "id",
          "type": "serial",
          "primaryKey": false,
          "notNull": true
        },
        "name": {
          "name": "name",
          "type": "text",
          "primaryKey": false,
          "notNull": true
        },
        "email": {
          "name": "email",
          "type": "varchar(255)",
          "primaryKey": true,
          "notNull": true
        },
        "password_hash": {
          "name": "password_hash",
          "type": "varchar(255)",
          "primaryKey": false,
          "notNull": true
        },
        "created_at": {
          "name": "created_at",
          "type": "timestamp",
          "primaryKey": false,
          "notNull": true,
          "default": "now()"
        }
      },
      "indexes": {},
      "foreignKeys": {},
      "compositePrimaryKeys": {},
      "uniqueConstraints": {}
    }
  },
  "enums": {},
  "schemas": {},
  "sequences": {},
  "_meta": {
    "columns": {},
    "schemas": {},
    "tables": {}
  }
}